{
  "name": "i3 - Monokai Pro - Github Dark",
  "type": "dark",
  "semanticHighlighting": true,
  "colors": {
    "focusBorder": "#1f6feb",
    "foreground": "#e6edf3",
    "descriptionForeground": "#7d8590",
    "errorForeground": "#f85149",
    "textLink.foreground": "#2f81f7",
    "textLink.activeForeground": "#2f81f7",
    "textBlockQuote.background": "#010409",
    "textBlockQuote.border": "#30363d",
    "textCodeBlock.background": "#6e768166",
    "textPreformat.foreground": "#7d8590",
    "textSeparator.foreground": "#21262d",
    "icon.foreground": "#7d8590",
    "keybindingLabel.foreground": "#e6edf3",
    "button.background": "#238636",
    "button.foreground": "#ffffff",
    "button.hoverBackground": "#2ea043",
    "button.secondaryBackground": "#282e33",
    "button.secondaryForeground": "#c9d1d9",
    "button.secondaryHoverBackground": "#30363d",
    "checkbox.background": "#161b22",
    "checkbox.border": "#30363d",
    "dropdown.background": "#161b22",
    "dropdown.border": "#30363d",
    "dropdown.foreground": "#e6edf3",
    "dropdown.listBackground": "#161b22",
    "input.background": "#0d1117",
    "input.border": "#30363d",
    "input.foreground": "#e6edf3",
    "input.placeholderForeground": "#6e7681",
    "badge.foreground": "#ffffff",
    "badge.background": "#1f6feb",
    "progressBar.background": "#1f6feb",
    "titleBar.activeForeground": "#7d8590",
    "titleBar.activeBackground": "#0d1117",
    "titleBar.inactiveForeground": "#7d8590",
    "titleBar.inactiveBackground": "#010409",
    "titleBar.border": "#30363d",
    "activityBar.foreground": "#e6edf3",
    "activityBar.inactiveForeground": "#7d8590",
    "activityBar.background": "#0d1117",
    "activityBarBadge.foreground": "#ffffff",
    "activityBarBadge.background": "#1f6feb",
    "activityBar.activeBorder": "#f78166",
    "activityBar.border": "#30363d",
    "sideBar.foreground": "#e6edf3",
    "sideBar.background": "#010409",
    "sideBar.border": "#30363d",
    "sideBarTitle.foreground": "#e6edf3",
    "sideBarSectionHeader.foreground": "#e6edf3",
    "sideBarSectionHeader.background": "#010409",
    "sideBarSectionHeader.border": "#30363d",
    "list.hoverForeground": "#e6edf3",
    "list.inactiveSelectionForeground": "#e6edf3",
    "list.activeSelectionForeground": "#e6edf3",
    "list.hoverBackground": "#6e76811a",
    "list.inactiveSelectionBackground": "#6e768166",
    "list.activeSelectionBackground": "#6e768166",
    "list.focusForeground": "#e6edf3",
    "list.focusBackground": "#388bfd26",
    "list.inactiveFocusBackground": "#388bfd26",
    "list.highlightForeground": "#2f81f7",
    "tree.indentGuidesStroke": "#21262d",
    "notificationCenterHeader.foreground": "#7d8590",
    "notificationCenterHeader.background": "#161b22",
    "notifications.foreground": "#e6edf3",
    "notifications.background": "#161b22",
    "notifications.border": "#30363d",
    "notificationsErrorIcon.foreground": "#f85149",
    "notificationsWarningIcon.foreground": "#d29922",
    "notificationsInfoIcon.foreground": "#2f81f7",
    "pickerGroup.border": "#30363d",
    "pickerGroup.foreground": "#7d8590",
    "quickInput.background": "#161b22",
    "quickInput.foreground": "#e6edf3",
    "statusBar.foreground": "#7d8590",
    "statusBar.background": "#0d1117",
    "statusBar.border": "#30363d",
    "statusBar.focusBorder": "#1f6feb80",
    "statusBar.noFolderBackground": "#0d1117",
    "statusBar.debuggingForeground": "#ffffff",
    "statusBar.debuggingBackground": "#da3633",
    "statusBarItem.prominentBackground": "#6e768166",
    "statusBarItem.remoteForeground": "#e6edf3",
    "statusBarItem.remoteBackground": "#30363d",
    "statusBarItem.hoverBackground": "#e6edf314",
    "statusBarItem.activeBackground": "#e6edf31f",
    "statusBarItem.focusBorder": "#1f6feb",
    "editorGroupHeader.tabsBackground": "#010409",
    "editorGroupHeader.tabsBorder": "#30363d",
    "editorGroup.border": "#30363d",
    "tab.activeForeground": "#e6edf3",
    "tab.inactiveForeground": "#7d8590",
    "tab.inactiveBackground": "#010409",
    "tab.activeBackground": "#0d1117",
    "tab.hoverBackground": "#0d1117",
    "tab.unfocusedHoverBackground": "#6e76811a",
    "tab.border": "#30363d",
    "tab.unfocusedActiveBorderTop": "#30363d",
    "tab.activeBorder": "#0d1117",
    "tab.unfocusedActiveBorder": "#0d1117",
    "tab.activeBorderTop": "#f78166",
    "breadcrumb.foreground": "#7d8590",
    "breadcrumb.focusForeground": "#e6edf3",
    "breadcrumb.activeSelectionForeground": "#7d8590",
    "breadcrumbPicker.background": "#161b22",
    "editor.background": "#0d1117",
    "editorWidget.background": "#161b22",
    "editor.foldBackground": "#6e76811a",
    "editor.lineHighlightBackground": "#6e76811a",
    "editorLineNumber.foreground": "#6e7681",
    "editorLineNumber.activeForeground": "#e6edf3",
    "editorIndentGuide.background": "#e6edf31f",
    "editorIndentGuide.activeBackground": "#e6edf33d",
    "editorWhitespace.foreground": "#484f58",
    "editorCursor.foreground": "#2f81f7",
    "editor.findMatchBackground": "#9e6a03",
    "editor.findMatchHighlightBackground": "#f2cc6080",
    "editor.linkedEditingBackground": "#2f81f712",
    "editor.selectionHighlightBackground": "#3fb95040",
    "editor.wordHighlightBackground": "#6e768180",
    "editor.wordHighlightBorder": "#6e768199",
    "editor.wordHighlightStrongBackground": "#6e76814d",
    "editor.wordHighlightStrongBorder": "#6e768199",
    "editorBracketMatch.background": "#3fb95040",
    "editorBracketMatch.border": "#3fb95099",
    "editorInlayHint.background": "#8b949e33",
    "editorInlayHint.foreground": "#7d8590",
    "editorInlayHint.typeBackground": "#8b949e33",
    "editorInlayHint.typeForeground": "#7d8590",
    "editorInlayHint.paramBackground": "#8b949e33",
    "editorInlayHint.paramForeground": "#7d8590",
    "editorGutter.modifiedBackground": "#bb800966",
    "editorGutter.addedBackground": "#2ea04366",
    "editorGutter.deletedBackground": "#f8514966",
    "diffEditor.insertedLineBackground": "#23863626",
    "diffEditor.insertedTextBackground": "#3fb9504d",
    "diffEditor.removedLineBackground": "#da363326",
    "diffEditor.removedTextBackground": "#ff7b724d",
    "scrollbar.shadow": "#484f5833",
    "scrollbarSlider.background": "#8b949e33",
    "scrollbarSlider.hoverBackground": "#8b949e3d",
    "scrollbarSlider.activeBackground": "#8b949e47",
    "editorOverviewRuler.border": "#010409",
    "minimapSlider.background": "#8b949e33",
    "minimapSlider.hoverBackground": "#8b949e3d",
    "minimapSlider.activeBackground": "#8b949e47",
    "panel.background": "#010409",
    "panel.border": "#30363d",
    "panelTitle.activeBorder": "#f78166",
    "panelTitle.activeForeground": "#e6edf3",
    "panelTitle.inactiveForeground": "#7d8590",
    "panelInput.border": "#30363d",
    "debugIcon.breakpointForeground": "#f85149",
    "debugConsole.infoForeground": "#8b949e",
    "debugConsole.warningForeground": "#d29922",
    "debugConsole.errorForeground": "#ffa198",
    "debugConsole.sourceForeground": "#e3b341",
    "debugConsoleInputIcon.foreground": "#bc8cff",
    "debugTokenExpression.name": "#79c0ff",
    "debugTokenExpression.value": "#a5d6ff",
    "debugTokenExpression.string": "#a5d6ff",
    "debugTokenExpression.boolean": "#56d364",
    "debugTokenExpression.number": "#56d364",
    "debugTokenExpression.error": "#ffa198",
    "symbolIcon.arrayForeground": "#f0883e",
    "symbolIcon.booleanForeground": "#58a6ff",
    "symbolIcon.classForeground": "#f0883e",
    "symbolIcon.colorForeground": "#79c0ff",
    "symbolIcon.constructorForeground": "#d2a8ff",
    "symbolIcon.enumeratorForeground": "#f0883e",
    "symbolIcon.enumeratorMemberForeground": "#58a6ff",
    "symbolIcon.eventForeground": "#6e7681",
    "symbolIcon.fieldForeground": "#f0883e",
    "symbolIcon.fileForeground": "#d29922",
    "symbolIcon.folderForeground": "#d29922",
    "symbolIcon.functionForeground": "#bc8cff",
    "symbolIcon.interfaceForeground": "#f0883e",
    "symbolIcon.keyForeground": "#58a6ff",
    "symbolIcon.keywordForeground": "#ff7b72",
    "symbolIcon.methodForeground": "#bc8cff",
    "symbolIcon.moduleForeground": "#ff7b72",
    "symbolIcon.namespaceForeground": "#ff7b72",
    "symbolIcon.nullForeground": "#58a6ff",
    "symbolIcon.numberForeground": "#3fb950",
    "symbolIcon.objectForeground": "#f0883e",
    "symbolIcon.operatorForeground": "#79c0ff",
    "symbolIcon.packageForeground": "#f0883e",
    "symbolIcon.propertyForeground": "#f0883e",
    "symbolIcon.referenceForeground": "#58a6ff",
    "symbolIcon.snippetForeground": "#58a6ff",
    "symbolIcon.stringForeground": "#79c0ff",
    "symbolIcon.structForeground": "#f0883e",
    "symbolIcon.textForeground": "#79c0ff",
    "symbolIcon.typeParameterForeground": "#79c0ff",
    "symbolIcon.unitForeground": "#58a6ff",
    "symbolIcon.variableForeground": "#f0883e",
    "symbolIcon.constantForeground": [
      "#aff5b4",
      "#7ee787",
      "#56d364",
      "#3fb950",
      "#2ea043",
      "#238636",
      "#196c2e",
      "#0f5323",
      "#033a16",
      "#04260f"
    ],
    "terminal.foreground": "#e6edf3",
    "terminal.ansiBlack": "#484f58",
    "terminal.ansiRed": "#ff7b72",
    "terminal.ansiGreen": "#3fb950",
    "terminal.ansiYellow": "#d29922",
    "terminal.ansiBlue": "#58a6ff",
    "terminal.ansiMagenta": "#bc8cff",
    "terminal.ansiCyan": "#39c5cf",
    "terminal.ansiWhite": "#b1bac4",
    "terminal.ansiBrightBlack": "#6e7681",
    "terminal.ansiBrightRed": "#ffa198",
    "terminal.ansiBrightGreen": "#56d364",
    "terminal.ansiBrightYellow": "#e3b341",
    "terminal.ansiBrightBlue": "#79c0ff",
    "terminal.ansiBrightMagenta": "#d2a8ff",
    "terminal.ansiBrightCyan": "#56d4dd",
    "terminal.ansiBrightWhite": "#ffffff",
    "gitDecoration.addedResourceForeground": "#3fb950",
    "gitDecoration.modifiedResourceForeground": "#d29922",
    "gitDecoration.deletedResourceForeground": "#f85149",
    "gitDecoration.untrackedResourceForeground": "#3fb950",
    "gitDecoration.ignoredResourceForeground": "#6e7681",
    "gitDecoration.conflictingResourceForeground": "#db6d28",
    "gitDecoration.submoduleResourceForeground": "#7d8590",
    "debugToolBar.background": "#161b22",
    "editor.stackFrameHighlightBackground": "#bb800966",
    "editor.focusedStackFrameHighlightBackground": "#2ea04366",
    "peekViewEditor.matchHighlightBackground": "#bb800966",
    "peekViewResult.matchHighlightBackground": "#bb800966",
    "peekViewEditor.background": "#6e76811a",
    "peekViewResult.background": "#0d1117",
    "settings.headerForeground": "#e6edf3",
    "settings.modifiedItemIndicator": "#bb800966",
    "welcomePage.buttonBackground": "#21262d",
    "welcomePage.buttonHoverBackground": "#30363d"
  },
  "tokenColors": [
    {
      "scope": [
        "comment",
        "comment keyword",
        "comment markup.underline.link",
        "comment string",
        "comment punctuation.definition",
        "comment punctuation",
        "comment text"
      ],
      "settings": {
        "name": "Comments and overrides inside comments",
        "fontStyle": "",
        "foreground": "#aca9ac"
      }
    },
    {
      "scope": "comment storage.type",
      "settings": {
        "name": "JSDoc storage type",
        "foreground": "#aca9ac"
      }
    },
    {
      "scope": "comment entity.name.type",
      "settings": {
        "name": "JSDoc entity name",
        "foreground": "#cac8c8"
      }
    },
    {
      "scope": [
        "comment variable",
        "comment variable.other"
      ],
      "settings": {
        "name": "JSDoc variable",
        "foreground": "#cac8c8"
      }
    },
    {
      "scope": [
        "comment keyword",
        "comment entity.name.tag",
        "entity.name.tag.documentation"
      ],
      "settings": {
        "name": "PHPDoc keyword",
        "foreground": "#cac8c8"
      }
    },
    {
      "scope": "comment keyword.codetag.notation",
      "settings": {
        "name": "Comment TODO / FIXME (at least in VSCode Python)",
        "foreground": "#b9a6ff"
      }
    },
    {
      "scope": "comment.git-status.header.remote",
      "settings": {
        "name": "Git status remote",
        "foreground": "#ff7095"
      }
    },
    {
      "scope": "comment.git-status.header.local",
      "settings": {
        "name": "Git status local",
        "foreground": "#78e6f2"
      }
    },
    {
      "scope": "comment.other.git-status.head",
      "settings": {
        "name": "Git status remote",
        "foreground": "#e5e5e4"
      }
    },
    {
      "scope": [
        "string.quoted.docstring",
        "string.quoted.docstring punctuation.definition"
      ],
      "settings": {
        "name": "Docstring",
        "foreground": "#aca9ac"
      }
    },
    {
      "scope": "constant",
      "settings": {
        "name": "Constant",
        "foreground": "#b9a6ff"
      }
    },
    {
      "scope": "constant.other",
      "settings": {
        "name": "Constant",
        "foreground": "#e5e5e4"
      }
    },
    {
      "scope": "constant.other.caps",
      "settings": {
        "name": "Constant",
        "foreground": "#b9a6ff"
      }
    },
    {
      "scope": "constant.other.placeholder.c",
      "settings": {
        "name": "Placeholders in C",
        "foreground": "#ffa758"
      }
    },
    {
      "scope": "constant.other.property",
      "settings": {
        "name": "Constant as property",
        "foreground": "#b9a6ff"
      }
    },
    {
      "scope": "constant.other.citation.latex",
      "settings": {
        "name": "Constant in latex",
        "foreground": "#b9a6ff"
      }
    },
    {
      "scope": "constant.other.color",
      "settings": {
        "name": "Constant as color (in css / sass)",
        "foreground": "#b9a6ff"
      }
    },
    {
      "scope": "constant.other.character-class.escape",
      "settings": {
        "name": "Constant as character class escape (e.g. in regex)",
        "foreground": "#b9a6ff"
      }
    },
    {
      "scope": "constant.other.key",
      "settings": {
        "name": "Constant as key (e.g. in puppet manifests)",
        "foreground": "#b9a6ff"
      }
    },
    {
      "scope": "constant.other.symbol",
      "settings": {
        "name": "Constant as symbol (e.g. in ruby)",
        "foreground": "#ffa758"
      }
    },
    {
      "scope": "constant.other.elm",
      "settings": {
        "name": "Constants in elm",
        "foreground": "#78e6f2"
      }
    },
    {
      "scope": "constant.numeric",
      "settings": {
        "name": "Number",
        "foreground": "#b9a6ff"
      }
    },
    {
      "scope": "constant.language",
      "settings": {
        "name": "Constant",
        "foreground": "#b9a6ff"
      }
    },
    {
      "scope": "constant.character.escape",
      "settings": {
        "name": "Character escape",
        "foreground": "#b9a6ff"
      }
    },
    {
      "scope": "constant.numeric.line-number.find-in-files",
      "settings": {
        "name": "Search result line numbers",
        "foreground": "#aca9ad"
      }
    },
    {
      "scope": "constant.numeric.line-number.match.find-in-files",
      "settings": {
        "name": "Search result matched line numbes",
        "foreground": "#ffe263"
      }
    },
    {
      "scope": "entity.name.section",
      "settings": {
        "name": "Sections",
        "foreground": "#ffe263"
      }
    },
    {
      "scope": [
        "entity.name.function",
        "entity.name.function.templated",
        "entity.name.function.member.static"
      ],
      "settings": {
        "name": "Functions",
        "foreground": "#ade676"
      }
    },
    {
      "scope": [
        "entity.name.type.class.templated",
        "entity.name.type.class.generic",
        "entity.name.type.namespace"
      ],
      "settings": {
        "name": "Class template",
        "foreground": "#78e6f2"
      }
    },
    {
      "scope": "entity.name.label",
      "settings": {
        "name": "label",
        "foreground": "#b9a6ff"
      }
    },
    {
      "scope": "entity.name.function.preprocessor",
      "settings": {
        "name": "Macros",
        "foreground": "#78e6f2"
      }
    },
    {
      "scope": "entity.name",
      "settings": {
        "name": "Entity name",
        "foreground": "#ade676"
      }
    },
    {
      "scope": "entity.name.class",
      "settings": {
        "name": "Class name",
        "foreground": "#78e6f2"
      }
    },
    {
      "scope": "entity.name.constant",
      "settings": {
        "name": "Constant name",
        "foreground": "#b9a6ff"
      }
    },
    {
      "scope": "entity.name.namespace",
      "settings": {
        "name": "Namespace",
        "foreground": "#e5e5e4"
      }
    },
    {
      "scope": "entity.other.inherited-class",
      "settings": {
        "name": "Inherited class",
        "fontStyle": "",
        "foreground": "#78e6f2"
      }
    },
    {
      "scope": "entity.name.function",
      "settings": {
        "name": "Function name",
        "foreground": "#ade676"
      }
    },
    {
      "scope": [
        "entity.name.tag",
        "entity.name.tag.js.jsx support.class.component.js.jsx",
        "entity.name.tag support.class.component",
        "source.vue support.class.component"
      ],
      "settings": {
        "name": "Tag name",
        "foreground": "#ff7095"
      }
    },
    {
      "scope": "entity.name.function.operator",
      "settings": {
        "name": "Operator",
        "foreground": "#ff7095"
      }
    },
    {
      "scope": [
        "meta.brackets entity.name.function.operator",
        "punctuation.separator entity.name.function.operator"
      ],
      "settings": {
        "name": "Operator",
        "foreground": "#abaaab"
      }
    },
    {
      "scope": [
        "entity.name.type",
        "entity.name.type.class.reference",
        "entity.name.type.class.value"
      ],
      "settings": {
        "name": "Entity name type",
        "foreground": "#78e6f2"
      }
    },
    {
      "scope": "entity.other.attribute-name",
      "settings": {
        "name": "Tag attribute",
        "fontStyle": "",
        "foreground": "#78e6f2"
      }
    },
    {
      "scope": [
        "entity.other.attribute-name.class.css",
        "entity.other.attribute-name.parent-selector-suffix.css",
        "entity.other.attribute-name.parent-selector-suffix.css punctuation.definition.entity.css",
        "entity.other.attribute-name.css",
        "entity.other.animation-name.css"
      ],
      "settings": {
        "name": "CSS class",
        "foreground": "#ade676"
      }
    },
    {
      "scope": "entity.other.attribute-name.id.css",
      "settings": {
        "name": "CSS id",
        "foreground": "#ffa758"
      }
    },
    {
      "scope": [
        "entity.other.attribute-name.pseudo-class.css",
        "entity.other.pseudo-class.css",
        "entity.other.pseudo-element.css"
      ],
      "settings": {
        "name": "CSS pseudo class",
        "fontStyle": "",
        "foreground": "#78e6f2"
      }
    },
    {
      "scope": [
        "entity.name.function",
        "support.function"
      ],
      "settings": {
        "name": "Function names / calls",
        "foreground": "#ade676"
      }
    },
    {
      "scope": "entity.other.git-status.hex",
      "settings": {
        "name": "git status commit hex",
        "foreground": "#b9a6ff"
      }
    },
    {
      "scope": "entity.other.jinja2.delimiter",
      "settings": {
        "name": "jinja delimiters",
        "foreground": "#abaaab"
      }
    },
    {
      "scope": "entity.name.operator.custom-literal",
      "settings": {
        "name": "custom literal",
        "foreground": "#e5e5e4"
      }
    },
    {
      "scope": "entity.name.operator.custom-literal.string",
      "settings": {
        "name": "custom literal string",
        "foreground": "#ffe263"
      }
    },
    {
      "scope": "entity.name.operator.custom-literal.number",
      "settings": {
        "name": "custom literal number",
        "foreground": "#b9a6ff"
      }
    },
    {
      "scope": "entity.name.type.rust",
      "settings": {
        "name": "rust specific",
        "foreground": "#78e6f2"
      }
    },
    {
      "scope": "entity.name.lifetime.rust",
      "settings": {
        "name": "rust specific",
        "foreground": "#ff7095"
      }
    },
    {
      "scope": "invalid",
      "settings": {
        "name": "Invalid",
        "foreground": "#ff7095",
        "fontStyle": "italic underline"
      }
    },
    {
      "scope": "invalid.deprecated",
      "settings": {
        "name": "Invalid deprecated",
        "foreground": "#ffa758",
        "fontStyle": "italic underline"
      }
    },
    {
      "scope": "keyword",
      "settings": {
        "name": "Keyword",
        "foreground": "#ff7095"
      }
    },
    {
      "scope": "keyword.control",
      "settings": {
        "name": "Control keywords examples include if, try, end and while. Some syntaxes prefer to mark if and else with the conditional variant. The import variant is often used in appropriate situations.",
        "foreground": "#ff7095"
      }
    },
    {
      "scope": "keyword.control.directive",
      "settings": {
        "name": "keyword control directive",
        "foreground": "#ff7095"
      }
    },
    {
      "scope": [
        "keyword.operator",
        "keyword.operator.member",
        "keyword.operator.new"
      ],
      "settings": {
        "name": "Operator",
        "foreground": "#ff7095"
      }
    },
    {
      "scope": "keyword.other.substitution",
      "settings": {
        "name": "Substitution string",
        "foreground": "#abaaab"
      }
    },
    {
      "scope": [
        "keyword.other.template.begin",
        "keyword.other.template.end"
      ],
      "settings": {
        "name": "Template literal begin / end",
        "foreground": "#ff7095"
      }
    },
    {
      "scope": [
        "keyword.operator.heading.restructuredtext",
        "keyword.operator.table.row.restructuredtext keyword.operator.table.data.restructuredtext"
      ],
      "settings": {
        "name": "RestructuredText heading, table markup",
        "foreground": "#abaaab"
      }
    },
    {
      "scope": "keyword.other.parenthesis.elm",
      "settings": {
        "name": "elm parenthesis",
        "foreground": "#abaaab"
      }
    },
    {
      "scope": [
        "keyword.other.fn.rust",
        "keyword.other.rust",
        "keyword.other.unsafe.rust",
        "keyword.other.where.rust"
      ],
      "settings": {
        "name": "rust specific",
        "foreground": "#78e6f2"
      }
    },
    {
      "scope": [
        "keyword.control.rust",
        "keyword.operator.misc.rust"
      ],
      "settings": {
        "name": "rust specific",
        "foreground": "#ff7095"
      }
    },
    {
      "scope": [
        "keyword.declaration.class.ruby",
        "keyword.declaration.function.ruby",
        "keyword.declaration.namespace.ruby"
      ],
      "settings": {
        "name": "ruby specific",
        "foreground": "#ff7095"
      }
    },
    {
      "scope": "markup.italic",
      "settings": {
        "name": "Italic",
        "fontStyle": ""
      }
    },
    {
      "scope": "markup.bold",
      "settings": {
        "name": "Bold",
        "fontStyle": "bold"
      }
    },
    {
      "scope": "markup.heading",
      "settings": {
        "name": "Heading",
        "foreground": "#ffe263"
      }
    },
    {
      "scope": "markup.raw",
      "settings": {
        "name": "Raw",
        "foreground": "#ffa758"
      }
    },
    {
      "scope": "markup.underline",
      "settings": {
        "name": "Underline",
        "fontStyle": "underline"
      }
    },
    {
      "scope": "markup.underline.link",
      "settings": {
        "name": "Link",
        "foreground": "#ade676"
      }
    },
    {
      "scope": [
        "markup.inserted",
        "markup.inserted punctuation.definition.inserted"
      ],
      "settings": {
        "name": "Diff inserted",
        "foreground": "#ade676"
      }
    },
    {
      "scope": [
        "markup.deleted",
        "markup.deleted punctuation.definition.deleted"
      ],
      "settings": {
        "name": "Diff deleted",
        "foreground": "#ff7095"
      }
    },
    {
      "scope": [
        "markup.changed",
        "markup.changed punctuation.definition.changed"
      ],
      "settings": {
        "name": "Diff changed",
        "foreground": "#ffe263"
      }
    },
    {
      "scope": [
        "markup.ignored",
        "markup.ignored punctuation.definition.ignored"
      ],
      "settings": {
        "name": "Diff ignored",
        "foreground": "#abaaab"
      }
    },
    {
      "scope": "markup.untracked",
      "settings": {
        "name": "Diff untracked",
        "foreground": "#abaaab"
      }
    },
    {
      "scope": "markup.quote",
      "settings": {
        "name": "Markup quote",
        "fontStyle": ""
      }
    },
    {
      "scope": [
        "meta.brace.round",
        "meta.brace.square",
        "meta.brace.curly",
        "meta.delimiter.comma.js",
        "meta.function-call.without-arguments.js",
        "meta.function-call.method.without-arguments.js"
      ],
      "settings": {
        "name": "Braces, delimiters",
        "foreground": "#abaaab"
      }
    },
    {
      "scope": [
        "meta.function-call.generic.python",
        "support.function.builtin.python"
      ],
      "settings": {
        "name": "Function call (vs)",
        "foreground": "#ade676"
      }
    },
    {
      "scope": "meta.function-call.python meta.function-call.arguments.python",
      "settings": {
        "name": "Function arguments (vs)",
        "foreground": "#e5e5e4"
      }
    },
    {
      "scope": "meta.instance.constructor",
      "settings": {
        "name": "Constructor (new MyClass())",
        "foreground": "#ade676"
      }
    },
    {
      "scope": [
        "meta.attribute-with-value.class string",
        "meta.attribute.class.html string"
      ],
      "settings": {
        "name": "Class string name (i.e. in html attributes)",
        "foreground": "#ade676"
      }
    },
    {
      "scope": [
        "meta.attribute-with-value.id string",
        "meta.attribute.id.html string"
      ],
      "settings": {
        "name": "ID string name (i.e. in html attributes)",
        "foreground": "#ffa758"
      }
    },
    {
      "scope": "source.json meta.mapping.key string",
      "settings": {
        "name": "JSON keys",
        "foreground": "#e5e5e4"
      }
    },
    {
      "scope": "source.yaml meta.mapping.key string",
      "settings": {
        "name": "YAML keys",
        "foreground": "#ff7095"
      }
    },
    {
      "scope": "meta.object.member",
      "settings": {
        "name": "Object members",
        "foreground": "#e5e5e4"
      }
    },
    {
      "scope": "meta.property-list.css variable.other",
      "settings": {
        "name": "SCSS Variable",
        "foreground": "#ffa758"
      }
    },
    {
      "scope": [
        "entity.name.constant.preprocessor",
        "meta.preprocessor"
      ],
      "settings": {
        "name": "Preprocessor",
        "foreground": "#b9a6ff"
      }
    },
    {
      "scope": "meta.diff.git-diff.header",
      "settings": {
        "name": "git diff header",
        "foreground": "#ffe263"
      }
    },
    {
      "scope": "meta.type_params.rust",
      "settings": {
        "name": "rust specific (brackets and certain type names)",
        "foreground": "#e5e5e4"
      }
    },
    {
      "scope": [
        "meta.attribute.rust",
        "meta.annotation.rust",
        "variable.language.rust",
        "variable.annotation.rust",
        "meta.annotation.rust string",
        "meta.annotation.rust keyword",
        "meta.annotation.rust keyword.operator",
        "meta.attribute.rust string"
      ],
      "settings": {
        "name": "rust specific (variable.language.rust is 'self' keyword.",
        "foreground": "#cac8c8"
      }
    },
    {
      "scope": [
        "meta.type variable",
        "meta.type variable.other.readwrite"
      ],
      "settings": {
        "name": "type annotation",
        "foreground": "#b9a6ff"
      }
    },
    {
      "scope": "punctuation",
      "settings": {
        "name": "Punctuation",
        "foreground": "#abaaab"
      }
    },
    {
      "scope": [
        "punctuation.definition.tag",
        "punctuation.definition.tag source",
        "punctuation.definition.group.begin.ruby",
        "punctuation.definition.group.end.ruby",
        "punctuation.definition.group.begin.css",
        "punctuation.definition.group.end.css",
        "punctuation.definition.string.end.html source.css",
        "punctuation.definition.block",
        "punctuation.definition.parameters.begin",
        "punctuation.definition.parameters.end",
        "punctuation.separator.parameter",
        "punctuation.accessor",
        "punctuation.terminator"
      ],
      "settings": {
        "name": "Punctuation tags",
        "foreground": "#abaaab"
      }
    },
    {
      "scope": "punctuation.definition.group",
      "settings": {
        "name": "Group (i.e. in regex)",
        "foreground": "#e5e5e4"
      }
    },
    {
      "scope": "punctuation.definition.comment",
      "settings": {
        "name": "Comment start / end",
        "foreground": "#aca9ac"
      }
    },
    {
      "scope": [
        "punctuation.definition.variable",
        "punctuation.definition.keyword.scss",
        "punctuation.definition.entity.css"
      ],
      "settings": {
        "name": "Variable indicator (i.e. in php or in include directives in sass)",
        "foreground": "#cac8c8"
      }
    },
    {
      "scope": [
        "punctuation.section.embedded",
        "punctuation.section.embedded entity.name.tag",
        "punctuation.section.embedded constant.other",
        "punctuation.section.embedded source",
        "punctuation.section.embedded.begin"
      ],
      "settings": {
        "name": "Punctuation section embedded (i.e. ?php blocks in html)",
        "foreground": "#ffa758"
      }
    },
    {
      "scope": [
        "punctuation.template-string.element.begin",
        "punctuation.template-string.element.end",
        "punctuation.definition.string.template.begin",
        "punctuation.definition.string.template.end",
        "string.quoted.template punctuation.definition.string.begin",
        "string.quoted.template punctuation.definition.string.end",
        "punctuation.definition.template-expression.begin",
        "punctuation.definition.template-expression.end"
      ],
      "settings": {
        "name": "Punctuation template string (`example`)",
        "foreground": "#ff7095"
      }
    },
    {
      "scope": [
        "meta.paragraph.markdown meta.dummy.line-break",
        "meta.paragraph.markdown meta.hard-line-break.markdown"
      ],
      "settings": {
        "name": "Punctuation hard line break in Markdown",
        "background": "#ab9df2"
      }
    },
    {
      "scope": "markup.underline.link punctuation",
      "settings": {
        "name": "Punctuation in markdown links",
        "foreground": "#ade676"
      }
    },
    {
      "scope": [
        "meta.brace.round",
        "meta.brace.square",
        "keyword.operator.type.annotation",
        "meta.type storage.modifier.array"
      ],
      "settings": {
        "name": "Meta braces",
        "foreground": "#abaaab"
      }
    },
    {
      "scope": "region.redish",
      "settings": {
        "name": "region red color",
        "foreground": "#ff7095",
        "background": "#ff618859"
      }
    },
    {
      "scope": "region.orangish",
      "settings": {
        "name": "region orange color",
        "foreground": "#ffa758",
        "background": "#fc986759"
      }
    },
    {
      "scope": "region.yellowish",
      "settings": {
        "name": "region yellow color",
        "foreground": "#ffe263",
        "background": "#ffd86659"
      }
    },
    {
      "scope": "region.greenish",
      "settings": {
        "name": "region green color",
        "foreground": "#ade676",
        "background": "#a9dc7659"
      }
    },
    {
      "scope": "region.bluish",
      "settings": {
        "name": "region blue color",
        "foreground": "#78e6f2",
        "background": "#78dce859"
      }
    },
    {
      "scope": "region.purplish",
      "settings": {
        "name": "region purple color",
        "foreground": "#b9a6ff",
        "background": "#ab9df259"
      }
    },
    {
      "scope": "region.pinkish",
      "settings": {
        "name": "region pink color",
        "foreground": "#ff7095",
        "background": "#ff618859"
      }
    },
    {
      "scope": "region.whitish",
      "settings": {
        "name": "White for ST3 for non-colorized scheme",
        "foreground": "#e5e5e5"
      }
    },
    {
      "scope": "source",
      "settings": {
        "name": "source",
        "foreground": "#e5e5e4"
      }
    },
    {
      "scope": [
        "source.scss",
        "source.sass"
      ],
      "settings": {
        "name": "SASS, SCSS default",
        "foreground": "#abaaab"
      }
    },
    {
      "scope": [
        "source.sass variable.other",
        "source.sass variable.sass",
        "source.scss variable.other",
        "source.scss variable.scss",
        "source.scss variable.sass",
        "source.css variable.other",
        "source.css variable.scss",
        "source.less variable.other",
        "source.less variable.other.less",
        "source.less variable.declaration.less"
      ],
      "settings": {
        "name": "SASS, SCSS and LESS variables",
        "fontStyle": "",
        "foreground": "#ffa758"
      }
    },
    {
      "scope": "source.git-show.commit.sha",
      "settings": {
        "name": "git",
        "foreground": "#b9a6ff"
      }
    },
    {
      "scope": [
        "source.git-show.author",
        "source.git-show.date",
        "source.git-diff.command",
        "source.git-diff.command meta.diff.git-diff.header.from-file",
        "source.git-diff.command meta.diff.git-diff.header.to-file"
      ],
      "settings": {
        "name": "git",
        "foreground": "#abaaab"
      }
    },
    {
      "scope": [
        "source.git-show meta.diff.git-diff.header.extended.index.from-sha",
        "source.git-show meta.diff.git-diff.header.extended.index.to-sha"
      ],
      "settings": {
        "name": "git diff header hash",
        "foreground": "#b9a6ff"
      }
    },
    {
      "scope": "source.git-show meta.diff.range.unified",
      "settings": {
        "name": "git diff header range",
        "foreground": "#ffa758"
      }
    },
    {
      "scope": [
        "source.git-show meta.diff.header.from-file",
        "source.git-show meta.diff.header.to-file"
      ],
      "settings": {
        "name": "git diff header files",
        "foreground": "#abaaab"
      }
    },
    {
      "scope": "storage",
      "settings": {
        "name": "Storage",
        "foreground": "#ff7095"
      }
    },
    {
      "scope": "storage.type",
      "settings": {
        "name": "Types and definition / declaration keywords should use the following scope. Examples include int, bool, char, func, function, class and def. Depending on the language and semantics, const may be this or storage.modifier.",
        "fontStyle": "",
        "foreground": "#78e6f2"
      }
    },
    {
      "scope": "storage.type.extends",
      "settings": {
        "name": "Extends",
        "fontStyle": "normal",
        "foreground": "#ff7095"
      }
    },
    {
      "scope": "storage.type.function.arrow",
      "settings": {
        "name": "Fat arrow function",
        "fontStyle": "normal",
        "foreground": "#ff7095"
      }
    },
    {
      "scope": [
        "storage.modifier",
        "storage.type.modifier"
      ],
      "settings": {
        "name": "Keywords that affect the storage of a variable, function or data structure should use the following scope. Examples include static, inline, const, public and private.",
        "fontStyle": "",
        "foreground": "#ff7095"
      }
    },
    {
      "scope": "storage.class.restructuredtext.ref",
      "settings": {
        "name": "refs (Restructured text)",
        "foreground": "#b9a6ff"
      }
    },
    {
      "scope": [
        "storage.modifier.visibility.rust",
        "storage.modifier.lifetime.rust"
      ],
      "settings": {
        "name": "rust specific",
        "foreground": "#ff7095"
      }
    },
    {
      "scope": [
        "storage.modifier.const.rust",
        "storage.modifier.dyn.rust",
        "storage.modifier.mut.rust",
        "storage.modifier.static.rust",
        "storage.type.rust",
        "storage.type.core.rust",
        "storage.class.std.rust"
      ],
      "settings": {
        "name": "rust specific",
        "foreground": "#78e6f2"
      }
    },
    {
      "scope": [
        "storage.type.rust",
        "storage.modifier.const.rust",
        "storage.modifier.dyn.rust",
        "storage.modifier.mut.rust",
        "storage.modifier.static.rust",
        "keyword.other.rust",
        "keyword.other.where.rust"
      ],
      "settings": {
        "name": "rust specific (adjust blue to red)",
        "foreground": "#ff7095"
      }
    },
    {
      "scope": "storage.modifier.import.java",
      "settings": {
        "name": "imported Java libraries",
        "foreground": "#e5e5e4"
      }
    },
    {
      "scope": "string",
      "settings": {
        "name": "String",
        "foreground": "#ffe263"
      }
    },
    {
      "scope": "string.unquoted.label",
      "settings": {
        "name": "String label",
        "foreground": "#e5e5e4"
      }
    },
    {
      "scope": "string source",
      "settings": {
        "name": "Source in template string",
        "foreground": "#e5e5e4"
      }
    },
    {
      "scope": [
        "string source punctuation.section.embedded",
        "string punctuation.definition.string source"
      ],
      "settings": {
        "name": "Embedded punctuation begin / end in template string",
        "foreground": "#abaaab"
      }
    },
    {
      "scope": [
        "string.other.link.title",
        "string.other.link.description"
      ],
      "settings": {
        "name": "link title",
        "foreground": "#ff7095"
      }
    },
    {
      "scope": "string.other.link.description.title",
      "settings": {
        "name": "link description",
        "foreground": "#78e6f2"
      }
    },
    {
      "scope": [
        "string.regexp punctuation.definition.string.begin",
        "string.regexp punctuation.definition.string.end"
      ],
      "settings": {
        "name": "String regexp begin / end",
        "foreground": "#ff7095"
      }
    },
    {
      "scope": [
        "string.other.ref",
        "string.other.restructuredtext.ref"
      ],
      "settings": {
        "name": "refs (Restructured text)",
        "foreground": "#ade676"
      }
    },
    {
      "scope": "string.other.git-status.help.key",
      "settings": {
        "name": "git key in git status help text",
        "foreground": "#cac8c8"
      }
    },
    {
      "scope": "string.other.git-status.remote",
      "settings": {
        "name": "git status remote",
        "foreground": "#ff7095"
      }
    },
    {
      "scope": "support.constant",
      "settings": {
        "name": "Library constant",
        "foreground": "#78e6f2"
      }
    },
    {
      "scope": "support.constant.handlebars",
      "settings": {
        "name": "Handlebars start / end",
        "foreground": "#abaaab"
      }
    },
    {
      "scope": "support.type.vendor-prefix.css",
      "settings": {
        "name": "vendor prefix",
        "foreground": "#cac8c8"
      }
    },
    {
      "scope": "support.function",
      "settings": {
        "name": "Function name",
        "foreground": "#ade676"
      }
    },
    {
      "scope": "support.function.delimiter.elm",
      "settings": {
        "name": "function brackets, comma's",
        "foreground": "#abaaab"
      }
    },
    {
      "scope": [
        "support.type",
        "entity.name.type.object.console"
      ],
      "settings": {
        "name": "Library type",
        "fontStyle": "",
        "foreground": "#78e6f2"
      }
    },
    {
      "scope": [
        "support.variable",
        "support.variable.property"
      ],
      "settings": {
        "name": "Support variables",
        "foreground": "#78e6f2"
      }
    },
    {
      "scope": "support.type.property-name",
      "settings": {
        "name": "Library type property, JSON keys",
        "fontStyle": "normal",
        "foreground": "#e5e5e4"
      }
    },
    {
      "scope": "support.class",
      "settings": {
        "name": "Library class",
        "foreground": "#78e6f2"
      }
    },
    {
      "scope": "support.constant.core.rust",
      "settings": {
        "name": "rust specific",
        "foreground": "#b9a6ff"
      }
    },
    {
      "scope": [
        "comment support",
        "comment support.class"
      ],
      "settings": {
        "name": "comment support",
        "foreground": "#aca9ac"
      }
    },
    {
      "scope": "text",
      "settings": {
        "name": "text",
        "foreground": "#e5e5e4"
      }
    },
    {
      "scope": "text.find-in-files",
      "settings": {
        "name": "Search result",
        "foreground": "#e5e5e4"
      }
    },
    {
      "scope": [
        "variable",
        "variable.other"
      ],
      "settings": {
        "name": "Variable",
        "foreground": "#e5e5e4"
      }
    },
    {
      "scope": [
        "variable.parameter",
        "parameters variable.function"
      ],
      "settings": {
        "name": "Function arguments",
        "fontStyle": "",
        "foreground": "#ffa758"
      }
    },
    {
      "scope": [
        "variable.language",
        "variable.parameter.function.language.special.self.python",
        "variable.parameter.function.language.special.cls.python"
      ],
      "settings": {
        "name": "Reserved variable names that are specified by the language, such as this, self, super, arguments. Also in function arguments (e.g. like in Python)",
        "fontStyle": "",
        "foreground": "#cac8c8"
      }
    },
    {
      "scope": "variable.language.arguments",
      "settings": {
        "name": "Reserved variable names: 'arguments'",
        "foreground": "#b9a6ff"
      }
    },
    {
      "scope": "variable.other.class",
      "settings": {
        "name": "Library function",
        "foreground": "#78e6f2"
      }
    },
    {
      "scope": "variable.other.constant",
      "settings": {
        "name": "Immutable variables, often via a const modifier, should receive the following scope. Depending on the language and semantics, entity.name.constant may be a better choice.",
        "foreground": "#b9a6ff"
      }
    },
    {
      "scope": "variable.other.readwrite",
      "settings": {
        "name": "read/write variables",
        "foreground": "#e5e5e4"
      }
    },
    {
      "scope": "variable.other.member",
      "settings": {
        "name": "Fields, properties, members and attributes of a class or other data structure should use:",
        "foreground": "#e5e5e4"
      }
    },
    {
      "scope": "variable.other.enummember",
      "settings": {
        "name": "Enum member",
        "foreground": "#b9a6ff"
      }
    },
    {
      "scope": [
        "variable.other.property",
        "variable.other.property.static",
        "variable.other.event"
      ],
      "settings": {
        "name": "Variable property",
        "foreground": "#e5e5e4"
      }
    },
    {
      "scope": "variable.function",
      "settings": {
        "name": "Function and method names should be scoped using the following, but only when they are being invoked. When defined, they should use entity.name.function.",
        "foreground": "#ade676"
      }
    },
    {
      "scope": "variable.other.substitution",
      "settings": {
        "name": "Substitution (restructured text)",
        "foreground": "#ffa758"
      }
    },
    {
      "scope": [
        "source.ruby variable.other.readwrite.instance.ruby",
        "source.ruby variable.other.readwrite.class.ruby"
      ],
      "settings": {
        "name": "Ruby instance variables",
        "foreground": "#b9a6ff"
      }
    },
    {
      "scope": "source.jinja2 variable.other.jinja2.block",
      "settings": {
        "name": "jinja2 variable block",
        "foreground": "#ade676"
      }
    },
    {
      "scope": "source.jinja2 variable.other.jinja2",
      "settings": {
        "name": "jinja2 variable",
        "foreground": "#ffa758"
      }
    }
  ]
}